src/__init__.py
src/uniqchars/__init__.py
src/uniqchars/main.py
src/uniqchars/app/__init__.py
src/uniqchars/app/app.py
src/uniqchars/utils/__init__.py
src/uniqchars/utils/exceptions.py
src/uniqchars/utils/functions.py
tests/__init__.py
uniqchars-1.2.dist-info/LICENSE
uniqchars-1.2.dist-info/METADATA
uniqchars-1.2.dist-info/WHEEL
uniqchars-1.2.dist-info/entry_points.txt
uniqchars-1.2.dist-info/top_level.txt
uniqchars-1.2.dist-info/RECORD
